{
  "slug": "huntress-l2",
  "vendor": "huntress",
  "level": "l2",
  "title": "Huntress for the engineer running the deployment",
  "summary": "Designing exclusions without blind spots, managing Defender from the Huntress console, enabling ITDR for a Microsoft 365 tenant, running an SAT campaign, and routing alerts into the PSA so nothing falls through the cracks.",
  "estimatedMinutes": 47,
  "prereqs": ["huntress-l1"],
  "lessons": [
    "01-policy-and-exclusion-design",
    "02-managed-defender",
    "03-enabling-itdr-for-m365",
    "04-running-an-sat-campaign",
    "05-psa-and-rmm-integration"
  ],
  "quiz": "huntress-l2-final",
  "status": "live"
}
